spicesor/__init__.py
spicesor-0.0.1.dist-info/LICENSE.txt
spicesor-0.0.1.dist-info/METADATA
spicesor-0.0.1.dist-info/WHEEL
spicesor-0.0.1.dist-info/top_level.txt
spicesor-0.0.1.dist-info/RECORD
