Metadata-Version: 2.1
Name: spicesor
Version: 0.0.1
Summary: A library or package to slice sparse tensors with one, two, or three dimensions
Home-page: https://github.com/andreasbrownethz/ISC2021-solutions/tree/main/assignment_8
Author: Andreas Brown
Author-email: browna@student.ethz.ch
License: MIT
Keywords: spicesor,slice,sparse,tensor
Platform: UNKNOWN
Classifier: Development Status :: 5 - Production/Stable
Classifier: Intended Audience :: Education
Classifier: Operating System :: Microsoft :: Windows :: Windows 10
Classifier: License :: OSI Approved :: MIT License
Classifier: Programming Language :: Python :: 3
Requires-Dist: numpy
Requires-Dist: tensorflow
